django_rest_api_logger/__init__.py
django_rest_api_logger/elasticsearch.py
django_rest_api_logger/logger.py
django_rest_api_logger/logging.py
django_rest_api_logger/mongo_config.py
django_rest_api_logger/utils.py
django_rest_api_logger-0.4.1.dist-info/METADATA
django_rest_api_logger-0.4.1.dist-info/WHEEL
django_rest_api_logger-0.4.1.dist-info/top_level.txt
django_rest_api_logger-0.4.1.dist-info/RECORD
