Metadata-Version: 2.1
Name: django-rest-api-logger
Version: 0.4.1
Summary: Log everything from your DRF view
Home-page: https://github.com/navidagz/django_rest_api_logger
Author: Navid Agz
Author-email: navidagz76@gmail.com
License: MIT
Platform: UNKNOWN
Classifier: License :: OSI Approved :: MIT License
Classifier: Programming Language :: Python :: 3
Classifier: Programming Language :: Python :: 3.6
Requires-Dist: pymongo
Requires-Dist: django
Requires-Dist: wheel
Requires-Dist: djangorestframework
Requires-Dist: elasticsearch
Requires-Dist: certifi
